pymillheat/__init__.py
pymillheat/errors.py
pymillheat/pymillheat.py
pymillheat-1.0.4.dist-info/LICENSE
pymillheat-1.0.4.dist-info/METADATA
pymillheat-1.0.4.dist-info/WHEEL
pymillheat-1.0.4.dist-info/top_level.txt
pymillheat-1.0.4.dist-info/RECORD
