Metadata-Version: 2.1
Name: pymillheat
Version: 1.0.4
Summary: Library for interacting with millheat api
Home-page: https://github.com/Erlendeikeland/pymillheat
Author: Erlendeikeland
Author-email: Erlend132@gmail.com
License: MIT
Platform: UNKNOWN
Classifier: Intended Audience :: Developers
Classifier: Operating System :: OS Independent
Classifier: License :: OSI Approved :: MIT License
Classifier: Programming Language :: Python :: 3.6
Classifier: Topic :: Software Development :: Libraries :: Python Modules
Requires-Python: >=3.5.3
Requires-Dist: aiohttp
Requires-Dist: async-timeout
Requires-Dist: urllib3
